GeeksforgeeksOperatingSystemsLectureNotes/README.md
GeeksforgeeksOperatingSystemsLectureNotes/__init__.py
GeeksforgeeksOperatingSystemsLectureNotes/__main__.py
GeeksforgeeksOperatingSystemsLectureNotes/file.epub
GeeksforgeeksOperatingSystemsLectureNotes/index.html
GeeksforgeeksOperatingSystemsLectureNotes/css/__init__.py
GeeksforgeeksOperatingSystemsLectureNotes/css/annotations.css
GeeksforgeeksOperatingSystemsLectureNotes/css/main.css
GeeksforgeeksOperatingSystemsLectureNotes/css/normalize.css
GeeksforgeeksOperatingSystemsLectureNotes/css/popup.css
GeeksforgeeksOperatingSystemsLectureNotes/font/__init__.py
GeeksforgeeksOperatingSystemsLectureNotes/font/fontello.eot
GeeksforgeeksOperatingSystemsLectureNotes/font/fontello.svg
GeeksforgeeksOperatingSystemsLectureNotes/font/fontello.ttf
GeeksforgeeksOperatingSystemsLectureNotes/font/fontello.woff
GeeksforgeeksOperatingSystemsLectureNotes/img/__init__.py
GeeksforgeeksOperatingSystemsLectureNotes/img/annotator-glyph-sprite.png
GeeksforgeeksOperatingSystemsLectureNotes/img/annotator-icon-sprite.png
GeeksforgeeksOperatingSystemsLectureNotes/img/apple-touch-icon.png
GeeksforgeeksOperatingSystemsLectureNotes/img/cancelfullscreen.png
GeeksforgeeksOperatingSystemsLectureNotes/img/close.png
GeeksforgeeksOperatingSystemsLectureNotes/img/fullscreen.png
GeeksforgeeksOperatingSystemsLectureNotes/img/loader.gif
GeeksforgeeksOperatingSystemsLectureNotes/img/menu-icon.png
GeeksforgeeksOperatingSystemsLectureNotes/img/save.png
GeeksforgeeksOperatingSystemsLectureNotes/img/saved.png
GeeksforgeeksOperatingSystemsLectureNotes/img/settings-s.png
GeeksforgeeksOperatingSystemsLectureNotes/img/settings.png
GeeksforgeeksOperatingSystemsLectureNotes/img/star.png
GeeksforgeeksOperatingSystemsLectureNotes/js/__init__.py
GeeksforgeeksOperatingSystemsLectureNotes/js/epub.js
GeeksforgeeksOperatingSystemsLectureNotes/js/epub.min.js
GeeksforgeeksOperatingSystemsLectureNotes/js/epub.min.map
GeeksforgeeksOperatingSystemsLectureNotes/js/hooks.min.js
geeksforgeeks_operating_systems_lecture_notes-2024.3.3.0.dist-info/METADATA
geeksforgeeks_operating_systems_lecture_notes-2024.3.3.0.dist-info/WHEEL
geeksforgeeks_operating_systems_lecture_notes-2024.3.3.0.dist-info/entry_points.txt
geeksforgeeks_operating_systems_lecture_notes-2024.3.3.0.dist-info/top_level.txt
geeksforgeeks_operating_systems_lecture_notes-2024.3.3.0.dist-info/RECORD
